README.rst
setup.cfg
setup.py
txrestapi/__init__.py
txrestapi/methods.py
txrestapi/resource.py
txrestapi/service.py
txrestapi/tests.py
txrestapi.egg-info/PKG-INFO
txrestapi.egg-info/SOURCES.txt
txrestapi.egg-info/dependency_links.txt
txrestapi.egg-info/entry_points.txt
txrestapi.egg-info/not-zip-safe
txrestapi.egg-info/top_level.txt