Metadata-Version: 1.0
Name: txrestapi
Version: 0.2
Summary: Easing the creation of REST API services in Python
Home-page: http://github.com/iancmcc/txrestapi
Author: Ian McCracken
Author-email: ian.mccracken@gmail.com
License: MIT
Platform: UNKNOWN
